odoo8_addon_l10n_br_sale_product-8.0.1.0.0.99.dev16-py2.7-nspkg.pth
odoo_addons/l10n_br_sale_product/__openerp__.py
odoo_addons/l10n_br_sale_product/__init__.py
odoo_addons/l10n_br_sale_product/README.rst
odoo_addons/l10n_br_sale_product/models/sale.py
odoo_addons/l10n_br_sale_product/models/__init__.py
odoo_addons/l10n_br_sale_product/models/res_company.py
odoo_addons/l10n_br_sale_product/i18n/pt_BR.po
odoo_addons/l10n_br_sale_product/views/sale_view.xml
odoo_addons/l10n_br_sale_product/views/res_company_view.xml
odoo_addons/l10n_br_sale_product/data/l10n_br_sale_product_data.xml
odoo_addons/l10n_br_sale_product/demo/product_demo.xml
odoo_addons/l10n_br_sale_product/static/description/icon.png
odoo8_addon_l10n_br_sale_product-8.0.1.0.0.99.dev16.dist-info/top_level.txt
odoo8_addon_l10n_br_sale_product-8.0.1.0.0.99.dev16.dist-info/WHEEL
odoo8_addon_l10n_br_sale_product-8.0.1.0.0.99.dev16.dist-info/RECORD
odoo8_addon_l10n_br_sale_product-8.0.1.0.0.99.dev16.dist-info/metadata.json
odoo8_addon_l10n_br_sale_product-8.0.1.0.0.99.dev16.dist-info/DESCRIPTION.rst
odoo8_addon_l10n_br_sale_product-8.0.1.0.0.99.dev16.dist-info/METADATA
odoo8_addon_l10n_br_sale_product-8.0.1.0.0.99.dev16.dist-info/namespace_packages.txt
